fastapi_async_crud_app_builder-0.1.0.dist-info/licenses/LICENSE
fastapi_builder/__init__.py
fastapi_builder/version.py
fastapi_builder/implementations/__init__.py
fastapi_builder/implementations/api_builder.py
fastapi_builder/implementations/auth_builder.py
fastapi_builder/implementations/router_factory.py
fastapi_builder/implementations/backend/__init__.py
fastapi_builder/implementations/backend/asyc_backend.py
fastapi_builder/implementations/parser/__init__.py
fastapi_builder/implementations/parser/basic_sampler.py
fastapi_builder/implementations/pluralizer/__init__.py
fastapi_builder/implementations/pluralizer/simple_pluralizer.py
fastapi_builder/implementations/rls/__init__.py
fastapi_builder/implementations/rls/owner.py
fastapi_builder/implementations/schemas/__init__.py
fastapi_builder/implementations/schemas/default_schema_factory.py
fastapi_builder/protocols/__init__.py
fastapi_builder/protocols/crud.py
fastapi_builder/protocols/pluralizer.py
fastapi_builder/protocols/rls_strategy.py
fastapi_builder/protocols/schema_factory.py
fastapi_builder/types/__init__.py
fastapi_builder/types/column_types.py
fastapi_builder/utils/__init__.py
fastapi_builder/utils/run_app.py
fastapi_async_crud_app_builder-0.1.0.dist-info/METADATA
fastapi_async_crud_app_builder-0.1.0.dist-info/WHEEL
fastapi_async_crud_app_builder-0.1.0.dist-info/top_level.txt
fastapi_async_crud_app_builder-0.1.0.dist-info/RECORD
